hombre_tools/__init__.py
hombre_tools/__main__.py
hombre_tools/pswd.py
hombre_tools/db/__init__.py
hombre_tools/db/db.py
hombre_tools/db/db_jde.py
hombre_tools/tools/__init__.py
hombre_tools/tools/data_profiling.py
hombre_tools/tools/jde_sql_decorate.py
hombre_tools/tools/metadata.py
hombre_tools/tools/catalog/__init__.py
hombre_tools/tools/catalog/catalog.py
hombre_tools/tools/catalog/catalog_new.h5
hombre_tools/utils/__init__.py
hombre_tools/utils/utils.py
hombre_tools-0.1.26.data/data/hombre_tools/tools/catalog/catalog_new.h5
hombre_tools-0.1.26.dist-info/LICENSE.txt
hombre_tools-0.1.26.dist-info/METADATA
hombre_tools-0.1.26.dist-info/WHEEL
hombre_tools-0.1.26.dist-info/top_level.txt
hombre_tools-0.1.26.dist-info/RECORD
